[{"win_team_name":"キリギリス","win_team_mvp":"KIRUA"},{"win_team_name":"キリギリス","win_team_mvp":"いし"},{"win_team_name":"キリギリス","win_team_mvp":"めいおー"},{"win_team_name":"キリギリス","win_team_mvp":"もとき"},{"win_team_name":"アリ","win_team_mvp":"REN"},{"win_team_name":"アリ","win_team_mvp":" わたる"},{"win_team_name":"アリ","win_team_mvp":"Luce"},{"win_team_name":"アリ","win_team_mvp":"ゆづさ"},{"win_team_name":"アリ","win_team_mvp":"レイシス"},{"win_team_name":"アリ","win_team_mvp":"こっでぃ"},{"win_team_name":"キリギリス","win_team_mvp":"わいわい"},{"win_team_name":"キリギリス","win_team_mvp":"138"},{"win_team_name":"アリ","win_team_mvp":"ひなた[S3]"},{"win_team_name":"キリギリス","win_team_mvp":"パンくん"},{"win_team_name":"アリ","win_team_mvp":"ひでき"},{"win_team_name":"アリ","win_team_mvp":"ホコ"},{"win_team_name":"キリギリス","win_team_mvp":"みみじろう"},{"win_team_name":"キリギリス","win_team_mvp":"フキゲン"},{"win_team_name":"キリギリス","win_team_mvp":"ハマグリ_ReV"},{"win_team_name":"キリギリス","win_team_mvp":"だい"},{"win_team_name":"アリ","win_team_mvp":"イカ(ひと)　SPT"},{"win_team_name":"キリギリス","win_team_mvp":"choisz"},{"win_team_name":"アリ","win_team_mvp":"むっちゃんGO♪"},{"win_team_name":"キリギリス","win_team_mvp":"とんこちゅ"},{"win_team_name":"アリ","win_team_mvp":"ナウ"},{"win_team_name":"キリギリス","win_team_mvp":"まゆか"},{"win_team_name":"アリ","win_team_mvp":"でんちち"},{"win_team_name":"アリ","win_team_mvp":"ゆっきー"},{"win_team_name":"キリギリス","win_team_mvp":"зима"},{"win_team_name":"アリ","win_team_mvp":"(´^ω^`)ワロチ"},{"win_team_name":"キリギリス","win_team_mvp":"さっちゃん"},{"win_team_name":"アリ","win_team_mvp":"まこ"},{"win_team_name":"アリ","win_team_mvp":"//"},{"win_team_name":"キリギリス","win_team_mvp":"yukkuri"},{"win_team_name":"キリギリス","win_team_mvp":"ゆんたん"},{"win_team_name":"キリギリス","win_team_mvp":"くなー"},{"win_team_name":"キリギリス","win_team_mvp":"v√²海²¤¼¾¡"},{"win_team_name":"アリ","win_team_mvp":"まめとしお"},{"win_team_name":"アリ","win_team_mvp":"SoU"},{"win_team_name":"アリ","win_team_mvp":"ゆうき×りょう"},{"win_team_name":"アリ","win_team_mvp":"ちくわぶ"},{"win_team_name":"キリギリス","win_team_mvp":"さぶ"},{"win_team_name":"アリ","win_team_mvp":"snow(・ω・`)"},{"win_team_name":"キリギリス","win_team_mvp":"しゅんぎょん"},{"win_team_name":"アリ","win_team_mvp":"このよのもの"},{"win_team_name":"キリギリス","win_team_mvp":"たん"},{"win_team_name":"キリギリス","win_team_mvp":"ちびペン★"},{"win_team_name":"アリ","win_team_mvp":"ほろんちゅ"},{"win_team_name":"アリ","win_team_mvp":"クロンガー"},{"win_team_name":"キリギリス","win_team_mvp":"291"},{"win_team_name":"アリ","win_team_mvp":"るい"},{"win_team_name":"アリ","win_team_mvp":"ふうりん"},{"win_team_name":"キリギリス","win_team_mvp":"äまくら"},{"win_team_name":"キリギリス","win_team_mvp":"ばーこー"},{"win_team_name":"キリギリス","win_team_mvp":"きょしょう"},{"win_team_name":"アリ","win_team_mvp":"あっちゃん##"},{"win_team_name":"キリギリス","win_team_mvp":"トミー☆"},{"win_team_name":"キリギリス","win_team_mvp":"キトラ"},{"win_team_name":"アリ","win_team_mvp":"でんち"},{"win_team_name":"キリギリス","win_team_mvp":"[        ]"},{"win_team_name":"キリギリス","win_team_mvp":"かな"},{"win_team_name":"キリギリス","win_team_mvp":"げんごろッス"},{"win_team_name":"キリギリス","win_team_mvp":"M78せいじん"},{"win_team_name":"キリギリス","win_team_mvp":"KuRa"},{"win_team_name":"アリ","win_team_mvp":"TK"},{"win_team_name":"アリ","win_team_mvp":"ライム"},{"win_team_name":"キリギリス","win_team_mvp":"catMa"},{"win_team_name":"アリ","win_team_mvp":"こうた"},{"win_team_name":"キリギリス","win_team_mvp":"ネオ"},{"win_team_name":"アリ","win_team_mvp":"リューク"},{"win_team_name":"アリ","win_team_mvp":"やな~シーサー"},{"win_team_name":"キリギリス","win_team_mvp":"ナタデココ"},{"win_team_name":"アリ","win_team_mvp":"バルグディス"},{"win_team_name":"キリギリス","win_team_mvp":"ひろき"},{"win_team_name":"キリギリス","win_team_mvp":"ゆりく"},{"win_team_name":"キリギリス","win_team_mvp":"ガミー"},{"win_team_name":"アリ","win_team_mvp":"ゼノス"},{"win_team_name":"アリ","win_team_mvp":"(*`ω´)"},{"win_team_name":"アリ","win_team_mvp":"びゅんびゅん"},{"win_team_name":"キリギリス","win_team_mvp":"ゆっきー"},{"win_team_name":"キリギリス","win_team_mvp":"в разведке"},{"win_team_name":"キリギリス","win_team_mvp":"カイ"},{"win_team_name":"キリギリス","win_team_mvp":"ヨースケ"},{"win_team_name":"キリギリス","win_team_mvp":"ころめる"},{"win_team_name":"キリギリス","win_team_mvp":"アヴァァアア"},{"win_team_name":"キリギリス","win_team_mvp":"ツヨシ"},{"win_team_name":"キリギリス","win_team_mvp":"ゆうと"},{"win_team_name":"アリ","win_team_mvp":"あじ"},{"win_team_name":"キリギリス","win_team_mvp":"おともんど"},{"win_team_name":"アリ","win_team_mvp":"こうき"},{"win_team_name":"アリ","win_team_mvp":"ぎんが"}]