[{"win_team_name":"キリギリス","win_team_mvp":"KAY"},{"win_team_name":"アリ","win_team_mvp":"Ym"},{"win_team_name":"アリ","win_team_mvp":"カンバ"},{"win_team_name":"アリ","win_team_mvp":"なつ"},{"win_team_name":"キリギリス","win_team_mvp":"たつみん"},{"win_team_name":"キリギリス","win_team_mvp":"たく"},{"win_team_name":"キリギリス","win_team_mvp":"ゲキダン"},{"win_team_name":"アリ","win_team_mvp":"ちゃんちー"},{"win_team_name":"アリ","win_team_mvp":"まみたす"},{"win_team_name":"キリギリス","win_team_mvp":"アイル"},{"win_team_name":"アリ","win_team_mvp":"セカンドハー"},{"win_team_name":"キリギリス","win_team_mvp":"ていとく"},{"win_team_name":"アリ","win_team_mvp":"ループくん"},{"win_team_name":"キリギリス","win_team_mvp":"たうか"},{"win_team_name":"アリ","win_team_mvp":"Akky"},{"win_team_name":"アリ","win_team_mvp":"ゆうちゃん"},{"win_team_name":"キリギリス","win_team_mvp":"ちゃちゃ"},{"win_team_name":"キリギリス","win_team_mvp":"コーラル"},{"win_team_name":"アリ","win_team_mvp":"ガンジー"},{"win_team_name":"キリギリス","win_team_mvp":"ここな"},{"win_team_name":"アリ","win_team_mvp":"てぃ"},{"win_team_name":"アリ","win_team_mvp":"ズケトモ"},{"win_team_name":"アリ","win_team_mvp":"ぐりしゃこ"},{"win_team_name":"キリギリス","win_team_mvp":"さうよ"},{"win_team_name":"アリ","win_team_mvp":"たっかー"},{"win_team_name":"キリギリス","win_team_mvp":"やなぎ"},{"win_team_name":"アリ","win_team_mvp":"リュウ3"},{"win_team_name":"キリギリス","win_team_mvp":"ことぶき"},{"win_team_name":"キリギリス","win_team_mvp":"とも~"},{"win_team_name":"キリギリス","win_team_mvp":"ごーるど"},{"win_team_name":"アリ","win_team_mvp":"みんみんお"},{"win_team_name":"キリギリス","win_team_mvp":"れんじ"},{"win_team_name":"キリギリス","win_team_mvp":"ヘッドアロー"},{"win_team_name":"キリギリス","win_team_mvp":"たけし"},{"win_team_name":"アリ","win_team_mvp":"ソラ"},{"win_team_name":"アリ","win_team_mvp":"sae:イカにんげ"},{"win_team_name":"キリギリス","win_team_mvp":"セノ/seno"},{"win_team_name":"アリ","win_team_mvp":"ひろみつ"},{"win_team_name":"アリ","win_team_mvp":"ココプ"},{"win_team_name":"キリギリス","win_team_mvp":"いちのせ♂ナ"},{"win_team_name":"キリギリス","win_team_mvp":"まぎ"},{"win_team_name":"キリギリス","win_team_mvp":"みみみ"},{"win_team_name":"キリギリス","win_team_mvp":"えり"},{"win_team_name":"アリ","win_team_mvp":"\u003e\u003c"},{"win_team_name":"アリ","win_team_mvp":"ジライヤ"},{"win_team_name":"アリ","win_team_mvp":"りく"},{"win_team_name":"キリギリス","win_team_mvp":"えふ"},{"win_team_name":"キリギリス","win_team_mvp":"てんちょー"},{"win_team_name":"アリ","win_team_mvp":"モロコシ"},{"win_team_name":"アリ","win_team_mvp":"パパ"},{"win_team_name":"キリギリス","win_team_mvp":"しょうた"},{"win_team_name":"アリ","win_team_mvp":"ガトー'ε'H\u0026M"},{"win_team_name":"キリギリス","win_team_mvp":"カレーそうめ"},{"win_team_name":"キリギリス","win_team_mvp":"くコ:ミ"},{"win_team_name":"キリギリス","win_team_mvp":"ていん*"},{"win_team_name":"キリギリス","win_team_mvp":"とち"},{"win_team_name":"アリ","win_team_mvp":"ぽっすん"},{"win_team_name":"アリ","win_team_mvp":"すず"},{"win_team_name":"アリ","win_team_mvp":"りぃん"},{"win_team_name":"アリ","win_team_mvp":"まちゃ"},{"win_team_name":"アリ","win_team_mvp":"こまったさん"},{"win_team_name":"アリ","win_team_mvp":"しなもそ"},{"win_team_name":"アリ","win_team_mvp":"アリトゥーン"},{"win_team_name":"キリギリス","win_team_mvp":"「よしくん」"},{"win_team_name":"キリギリス","win_team_mvp":"folklore"},{"win_team_name":"キリギリス","win_team_mvp":"yu/u!!"},{"win_team_name":"アリ","win_team_mvp":"けさお"},{"win_team_name":"アリ","win_team_mvp":"もんこちゃん_M"},{"win_team_name":"アリ","win_team_mvp":"よっしー"},{"win_team_name":"アリ","win_team_mvp":"ココ☆チーノ"},{"win_team_name":"キリギリス","win_team_mvp":"あんこ"},{"win_team_name":"キリギリス","win_team_mvp":"モエパセ"},{"win_team_name":"キリギリス","win_team_mvp":"トウヨウのROBO"},{"win_team_name":"キリギリス","win_team_mvp":"ゆん"},{"win_team_name":"アリ","win_team_mvp":"banana"},{"win_team_name":"キリギリス","win_team_mvp":"ふじー"},{"win_team_name":"アリ","win_team_mvp":"ノノグラム.EXE"},{"win_team_name":"キリギリス","win_team_mvp":"ありがとウッ"},{"win_team_name":"キリギリス","win_team_mvp":"プギマロ"},{"win_team_name":"キリギリス","win_team_mvp":"tony"},{"win_team_name":"アリ","win_team_mvp":"サイロック"},{"win_team_name":"アリ","win_team_mvp":"ベリーズ"},{"win_team_name":"アリ","win_team_mvp":"ソラネス*ゆき"},{"win_team_name":"アリ","win_team_mvp":"みのぢ"},{"win_team_name":"アリ","win_team_mvp":"LIGHTNING"},{"win_team_name":"アリ","win_team_mvp":"りむっち"},{"win_team_name":"キリギリス","win_team_mvp":"アトム"},{"win_team_name":"アリ","win_team_mvp":"ひまさん"},{"win_team_name":"キリギリス","win_team_mvp":"ミッキーマウ"},{"win_team_name":"アリ","win_team_mvp":"うろつき"},{"win_team_name":"キリギリス","win_team_mvp":"むへちせむの"}]