[{"win_team_name":"キリギリス","win_team_mvp":"ウルクスス"},{"win_team_name":"アリ","win_team_mvp":"りゅうりゅう®"},{"win_team_name":"キリギリス","win_team_mvp":"ピヨ"},{"win_team_name":"アリ","win_team_mvp":"とらねこ"},{"win_team_name":"アリ","win_team_mvp":"ひんちゃん"},{"win_team_name":"キリギリス","win_team_mvp":"せんたろう"},{"win_team_name":"キリギリス","win_team_mvp":"yt-zi"},{"win_team_name":"アリ","win_team_mvp":"DJフリムキ"},{"win_team_name":"アリ","win_team_mvp":"しがらみ"},{"win_team_name":"キリギリス","win_team_mvp":"ジュン"},{"win_team_name":"アリ","win_team_mvp":"きみきみ"},{"win_team_name":"キリギリス","win_team_mvp":"キョドヘルカ"},{"win_team_name":"アリ","win_team_mvp":"せいや"},{"win_team_name":"キリギリス","win_team_mvp":"むぎちゃ"},{"win_team_name":"キリギリス","win_team_mvp":"とーばるど"},{"win_team_name":"キリギリス","win_team_mvp":"フィン・ファ"},{"win_team_name":"アリ","win_team_mvp":"ひまお"},{"win_team_name":"キリギリス","win_team_mvp":"ゆぽんこ"},{"win_team_name":"キリギリス","win_team_mvp":"つばあず\u003eω\u003c"},{"win_team_name":"キリギリス","win_team_mvp":"やまChan"},{"win_team_name":"キリギリス","win_team_mvp":"まーぼー"},{"win_team_name":"キリギリス","win_team_mvp":"☆★TaKuMi★☆"},{"win_team_name":"アリ","win_team_mvp":"トマリ"},{"win_team_name":"キリギリス","win_team_mvp":"Somany"},{"win_team_name":"キリギリス","win_team_mvp":"うめとキリギ"},{"win_team_name":"キリギリス","win_team_mvp":"ぽとふ"},{"win_team_name":"キリギリス","win_team_mvp":"まだお"},{"win_team_name":"キリギリス","win_team_mvp":"chanmaai"},{"win_team_name":"キリギリス","win_team_mvp":"るき"},{"win_team_name":"キリギリス","win_team_mvp":"tomato"},{"win_team_name":"アリ","win_team_mvp":"hisa"},{"win_team_name":"キリギリス","win_team_mvp":"レイド"},{"win_team_name":"キリギリス","win_team_mvp":"まめチビ"},{"win_team_name":"アリ","win_team_mvp":"もーい"},{"win_team_name":"キリギリス","win_team_mvp":"あかてん"},{"win_team_name":"キリギリス","win_team_mvp":"イカフライ"},{"win_team_name":"キリギリス","win_team_mvp":"じゅん"},{"win_team_name":"キリギリス","win_team_mvp":"みそづけ"},{"win_team_name":"キリギリス","win_team_mvp":"サスケェ"},{"win_team_name":"キリギリス","win_team_mvp":"soylatte"},{"win_team_name":"キリギリス","win_team_mvp":"たけひろ"},{"win_team_name":"アリ","win_team_mvp":"Ww_yuta_wW"},{"win_team_name":"アリ","win_team_mvp":"にゃむねこ"},{"win_team_name":"キリギリス","win_team_mvp":"みみ"},{"win_team_name":"キリギリス","win_team_mvp":"まこたん"},{"win_team_name":"キリギリス","win_team_mvp":"りんご"},{"win_team_name":"キリギリス","win_team_mvp":"KIRA"},{"win_team_name":"キリギリス","win_team_mvp":"ほのか"},{"win_team_name":"キリギリス","win_team_mvp":"Dude"},{"win_team_name":"アリ","win_team_mvp":"えいえんのせ"},{"win_team_name":"キリギリス","win_team_mvp":"バニラ"},{"win_team_name":"キリギリス","win_team_mvp":"しろ"},{"win_team_name":"アリ","win_team_mvp":"すず"},{"win_team_name":"アリ","win_team_mvp":"ふじの"},{"win_team_name":"キリギリス","win_team_mvp":"もっきょ"},{"win_team_name":"キリギリス","win_team_mvp":"つくね"},{"win_team_name":"アリ","win_team_mvp":"かなお"},{"win_team_name":"キリギリス","win_team_mvp":"いろはす"},{"win_team_name":"アリ","win_team_mvp":"ゆっくりsurizu"},{"win_team_name":"キリギリス","win_team_mvp":"ヤンター"},{"win_team_name":"キリギリス","win_team_mvp":"らぁめ"},{"win_team_name":"キリギリス","win_team_mvp":"ラスカル"},{"win_team_name":"キリギリス","win_team_mvp":"RX-0"},{"win_team_name":"キリギリス","win_team_mvp":"イカだいこん"},{"win_team_name":"アリ","win_team_mvp":"ワニワニパニ"},{"win_team_name":"キリギリス","win_team_mvp":"Mibu"},{"win_team_name":"キリギリス","win_team_mvp":"エネ"},{"win_team_name":"キリギリス","win_team_mvp":"まひろ"},{"win_team_name":"アリ","win_team_mvp":"29ZR"},{"win_team_name":"キリギリス","win_team_mvp":"あーみん"},{"win_team_name":"キリギリス","win_team_mvp":"しろかわ"},{"win_team_name":"キリギリス","win_team_mvp":"まなしゃん"},{"win_team_name":"キリギリス","win_team_mvp":"ハヤオ"},{"win_team_name":"アリ","win_team_mvp":"ゆーくん"},{"win_team_name":"アリ","win_team_mvp":"フルオウ"},{"win_team_name":"アリ","win_team_mvp":"まひろん"},{"win_team_name":"キリギリス","win_team_mvp":"うし"},{"win_team_name":"アリ","win_team_mvp":"ヘイチョー"},{"win_team_name":"アリ","win_team_mvp":"すぷこ"},{"win_team_name":"キリギリス","win_team_mvp":"いたのおねえ"},{"win_team_name":"アリ","win_team_mvp":"せな"},{"win_team_name":"キリギリス","win_team_mvp":"$RYO$"},{"win_team_name":"キリギリス","win_team_mvp":"ポーロ"},{"win_team_name":"アリ","win_team_mvp":"あきと"},{"win_team_name":"キリギリス","win_team_mvp":"タッキー"},{"win_team_name":"アリ","win_team_mvp":"はぐれメタルB"},{"win_team_name":"キリギリス","win_team_mvp":"イカミリン"},{"win_team_name":"キリギリス","win_team_mvp":"じまみ"},{"win_team_name":"アリ","win_team_mvp":"ゆうた"},{"win_team_name":"アリ","win_team_mvp":"ZEN"},{"win_team_name":"キリギリス","win_team_mvp":"いーあーる"}]