[{"win_team_name":"緑のたぬき","win_team_mvp":"ingktr"},{"win_team_name":"赤いきつね","win_team_mvp":"スゥ"},{"win_team_name":"緑のたぬき","win_team_mvp":"あすとTKD"},{"win_team_name":"赤いきつね","win_team_mvp":"きゃろる"},{"win_team_name":"赤いきつね","win_team_mvp":"suikwasha"},{"win_team_name":"赤いきつね","win_team_mvp":"APEL"},{"win_team_name":"赤いきつね","win_team_mvp":"にせまきマキ"},{"win_team_name":"赤いきつね","win_team_mvp":"あのやまいも"},{"win_team_name":"赤いきつね","win_team_mvp":"はる"},{"win_team_name":"緑のたぬき","win_team_mvp":"へいじver.3"},{"win_team_name":"赤いきつね","win_team_mvp":"くまみそ"},{"win_team_name":"赤いきつね","win_team_mvp":"トン"},{"win_team_name":"赤いきつね","win_team_mvp":"よう"},{"win_team_name":"赤いきつね","win_team_mvp":"rukari"},{"win_team_name":"赤いきつね","win_team_mvp":"ふぉん"},{"win_team_name":"赤いきつね","win_team_mvp":"あと"},{"win_team_name":"赤いきつね","win_team_mvp":"feat.SaeJa"},{"win_team_name":"赤いきつね","win_team_mvp":"アールグレイ"},{"win_team_name":"赤いきつね","win_team_mvp":"rein"},{"win_team_name":"赤いきつね","win_team_mvp":"えむえむ"},{"win_team_name":"緑のたぬき","win_team_mvp":"ほろよい"},{"win_team_name":"緑のたぬき","win_team_mvp":"てっちー"},{"win_team_name":"赤いきつね","win_team_mvp":"とき"},{"win_team_name":"赤いきつね","win_team_mvp":"ねこまんま"},{"win_team_name":"緑のたぬき","win_team_mvp":"るふぁ"},{"win_team_name":"緑のたぬき","win_team_mvp":"マヒャ・ド"},{"win_team_name":"緑のたぬき","win_team_mvp":"サンクト"},{"win_team_name":"赤いきつね","win_team_mvp":"あおきゃん"},{"win_team_name":"赤いきつね","win_team_mvp":"naoki"},{"win_team_name":"緑のたぬき","win_team_mvp":"ハイエース A+99"},{"win_team_name":"緑のたぬき","win_team_mvp":"カカカミ"},{"win_team_name":"緑のたぬき","win_team_mvp":"じゅじゅ"},{"win_team_name":"緑のたぬき","win_team_mvp":"なみだめです"},{"win_team_name":"緑のたぬき","win_team_mvp":"ぽんず"},{"win_team_name":"赤いきつね","win_team_mvp":"まー"},{"win_team_name":"緑のたぬき","win_team_mvp":"マルパン©"},{"win_team_name":"緑のたぬき","win_team_mvp":"プニャコ"},{"win_team_name":"赤いきつね","win_team_mvp":"ひー"},{"win_team_name":"赤いきつね","win_team_mvp":"りょ"},{"win_team_name":"緑のたぬき","win_team_mvp":"yuri"},{"win_team_name":"緑のたぬき","win_team_mvp":"ごちうさきん"},{"win_team_name":"赤いきつね","win_team_mvp":"ほり"},{"win_team_name":"赤いきつね","win_team_mvp":"【PANDA】"},{"win_team_name":"緑のたぬき","win_team_mvp":"あのポン"},{"win_team_name":"緑のたぬき","win_team_mvp":"ハヤ"},{"win_team_name":"赤いきつね","win_team_mvp":"Mr.GDP"},{"win_team_name":"赤いきつね","win_team_mvp":"みつな"},{"win_team_name":"赤いきつね","win_team_mvp":"ぐれい"},{"win_team_name":"緑のたぬき","win_team_mvp":"ひすい"},{"win_team_name":"赤いきつね","win_team_mvp":"どらまさ"},{"win_team_name":"赤いきつね","win_team_mvp":"すすす"},{"win_team_name":"赤いきつね","win_team_mvp":"mhz"},{"win_team_name":"緑のたぬき","win_team_mvp":"ぎょうざ"},{"win_team_name":"赤いきつね","win_team_mvp":"しゅんた"},{"win_team_name":"赤いきつね","win_team_mvp":"natu"},{"win_team_name":"赤いきつね","win_team_mvp":"ポルコ"},{"win_team_name":"赤いきつね","win_team_mvp":"のあと"},{"win_team_name":"緑のたぬき","win_team_mvp":"もっさりした"},{"win_team_name":"緑のたぬき","win_team_mvp":"まゆみ"},{"win_team_name":"赤いきつね","win_team_mvp":"フィンネ・ハ"},{"win_team_name":"緑のたぬき","win_team_mvp":"やまちよ"},{"win_team_name":"緑のたぬき","win_team_mvp":"おやつカルパ"},{"win_team_name":"緑のたぬき","win_team_mvp":"ぱぱ"},{"win_team_name":"緑のたぬき","win_team_mvp":"メルトン"},{"win_team_name":"緑のたぬき","win_team_mvp":"ノリス"},{"win_team_name":"緑のたぬき","win_team_mvp":"penguin"},{"win_team_name":"赤いきつね","win_team_mvp":"キングクリボ"},{"win_team_name":"赤いきつね","win_team_mvp":"モリヤマサト"},{"win_team_name":"緑のたぬき","win_team_mvp":"たぬきゆうい"},{"win_team_name":"赤いきつね","win_team_mvp":"ロシアスキー"},{"win_team_name":"赤いきつね","win_team_mvp":"マグロマン"},{"win_team_name":"緑のたぬき","win_team_mvp":"raki"},{"win_team_name":"緑のたぬき","win_team_mvp":"ことま"},{"win_team_name":"赤いきつね","win_team_mvp":"しゅん3"},{"win_team_name":"赤いきつね","win_team_mvp":"MarshalI"},{"win_team_name":"緑のたぬき","win_team_mvp":"あきら"},{"win_team_name":"赤いきつね","win_team_mvp":"リリー"},{"win_team_name":"緑のたぬき","win_team_mvp":"rideru"},{"win_team_name":"緑のたぬき","win_team_mvp":"misao"},{"win_team_name":"赤いきつね","win_team_mvp":"おおたにさん"},{"win_team_name":"赤いきつね","win_team_mvp":"HUDSON"},{"win_team_name":"緑のたぬき","win_team_mvp":"sadamunにほん"},{"win_team_name":"赤いきつね","win_team_mvp":"ザックス"},{"win_team_name":"赤いきつね","win_team_mvp":"ゲソのきわみ"},{"win_team_name":"赤いきつね","win_team_mvp":"itota"},{"win_team_name":"赤いきつね","win_team_mvp":"kuroneko"},{"win_team_name":"緑のたぬき","win_team_mvp":"カル~ア"},{"win_team_name":"赤いきつね","win_team_mvp":"りゃりゅりょ"},{"win_team_name":"赤いきつね","win_team_mvp":"ブキニン"},{"win_team_name":"緑のたぬき","win_team_mvp":"みれん"},{"win_team_name":"緑のたぬき","win_team_mvp":"けんじ"}]