[{"win_team_name":"緑のたぬき","win_team_mvp":"かずま"},{"win_team_name":"赤いきつね","win_team_mvp":"やよいおり。"},{"win_team_name":"緑のたぬき","win_team_mvp":"ぐみ"},{"win_team_name":"赤いきつね","win_team_mvp":"ミニピンコ"},{"win_team_name":"赤いきつね","win_team_mvp":"WIIU"},{"win_team_name":"緑のたぬき","win_team_mvp":"りっくん"},{"win_team_name":"赤いきつね","win_team_mvp":"たぬき"},{"win_team_name":"緑のたぬき","win_team_mvp":"ミちる"},{"win_team_name":"緑のたぬき","win_team_mvp":"はると"},{"win_team_name":"緑のたぬき","win_team_mvp":"まーくん"},{"win_team_name":"緑のたぬき","win_team_mvp":"09ちるの"},{"win_team_name":"緑のたぬき","win_team_mvp":"ようじ"},{"win_team_name":"赤いきつね","win_team_mvp":"002"},{"win_team_name":"緑のたぬき","win_team_mvp":"いろはぁす"},{"win_team_name":"赤いきつね","win_team_mvp":"やこ"},{"win_team_name":"緑のたぬき","win_team_mvp":"よし"},{"win_team_name":"緑のたぬき","win_team_mvp":"みっつ"},{"win_team_name":"赤いきつね","win_team_mvp":"ケニー"},{"win_team_name":"赤いきつね","win_team_mvp":"びちぐそ"},{"win_team_name":"緑のたぬき","win_team_mvp":"あずきバー"},{"win_team_name":"赤いきつね","win_team_mvp":"しゃもじ"},{"win_team_name":"赤いきつね","win_team_mvp":"マルフォイ"},{"win_team_name":"緑のたぬき","win_team_mvp":"レインボー"},{"win_team_name":"赤いきつね","win_team_mvp":"らっこ"},{"win_team_name":"緑のたぬき","win_team_mvp":"ふわとろにこ"},{"win_team_name":"緑のたぬき","win_team_mvp":"じゅん"},{"win_team_name":"赤いきつね","win_team_mvp":"イカリング"},{"win_team_name":"赤いきつね","win_team_mvp":"かなかな"},{"win_team_name":"赤いきつね","win_team_mvp":"ノヘ"},{"win_team_name":"赤いきつね","win_team_mvp":"shady_haze"},{"win_team_name":"緑のたぬき","win_team_mvp":"OSOTO"},{"win_team_name":"緑のたぬき","win_team_mvp":"おだやか"},{"win_team_name":"赤いきつね","win_team_mvp":"みけらんじぇ"},{"win_team_name":"赤いきつね","win_team_mvp":"EMMA"},{"win_team_name":"緑のたぬき","win_team_mvp":"シェイラコロ"},{"win_team_name":"緑のたぬき","win_team_mvp":"トクモリ"},{"win_team_name":"赤いきつね","win_team_mvp":"のーねーむ"},{"win_team_name":"緑のたぬき","win_team_mvp":"ふりびす"},{"win_team_name":"赤いきつね","win_team_mvp":"こあるひー"},{"win_team_name":"緑のたぬき","win_team_mvp":"すあま"},{"win_team_name":"緑のたぬき","win_team_mvp":"しょーご"},{"win_team_name":"緑のたぬき","win_team_mvp":"りく"},{"win_team_name":"緑のたぬき","win_team_mvp":"げるしー"},{"win_team_name":"赤いきつね","win_team_mvp":"ねこっぽ"},{"win_team_name":"緑のたぬき","win_team_mvp":"ごはん～☆HL"},{"win_team_name":"緑のたぬき","win_team_mvp":"Ranhu.N"},{"win_team_name":"緑のたぬき","win_team_mvp":"ぞんび"},{"win_team_name":"緑のたぬき","win_team_mvp":"りっくん"},{"win_team_name":"緑のたぬき","win_team_mvp":"シキ"},{"win_team_name":"緑のたぬき","win_team_mvp":"meteor"},{"win_team_name":"緑のたぬき","win_team_mvp":"おため"},{"win_team_name":"緑のたぬき","win_team_mvp":"ヤンキー。"},{"win_team_name":"緑のたぬき","win_team_mvp":"えねまめ"},{"win_team_name":"緑のたぬき","win_team_mvp":"qXeL_"},{"win_team_name":"緑のたぬき","win_team_mvp":"まー"},{"win_team_name":"赤いきつね","win_team_mvp":"パフ"},{"win_team_name":"赤いきつね","win_team_mvp":"キッチョム"},{"win_team_name":"緑のたぬき","win_team_mvp":"アッキー"},{"win_team_name":"赤いきつね","win_team_mvp":"マサタカ"},{"win_team_name":"緑のたぬき","win_team_mvp":"ココяシオカラ"},{"win_team_name":"緑のたぬき","win_team_mvp":"つち"},{"win_team_name":"赤いきつね","win_team_mvp":"Tsubasa"},{"win_team_name":"緑のたぬき","win_team_mvp":"tm_deck"},{"win_team_name":"赤いきつね","win_team_mvp":"にこにー"},{"win_team_name":"赤いきつね","win_team_mvp":"ひびき"},{"win_team_name":"赤いきつね","win_team_mvp":"T=nb"},{"win_team_name":"赤いきつね","win_team_mvp":"きのこ/o.p.t"},{"win_team_name":"緑のたぬき","win_team_mvp":"セクト"},{"win_team_name":"緑のたぬき","win_team_mvp":"ヌメモン"},{"win_team_name":"赤いきつね","win_team_mvp":"きょうのニャ"},{"win_team_name":"赤いきつね","win_team_mvp":"ぷりん"},{"win_team_name":"緑のたぬき","win_team_mvp":"てぺぺ"},{"win_team_name":"緑のたぬき","win_team_mvp":"こいしちゃん"},{"win_team_name":"緑のたぬき","win_team_mvp":"ちち"},{"win_team_name":"緑のたぬき","win_team_mvp":"きつち"},{"win_team_name":"赤いきつね","win_team_mvp":"かつ"},{"win_team_name":"赤いきつね","win_team_mvp":"ましむ"},{"win_team_name":"赤いきつね","win_team_mvp":"ピサのしゃと"},{"win_team_name":"緑のたぬき","win_team_mvp":"おけいはん"},{"win_team_name":"緑のたぬき","win_team_mvp":"マカロン☆"},{"win_team_name":"赤いきつね","win_team_mvp":"BTS(ブッツ)"},{"win_team_name":"緑のたぬき","win_team_mvp":"べんがる"},{"win_team_name":"緑のたぬき","win_team_mvp":"いとうたいい"},{"win_team_name":"赤いきつね","win_team_mvp":"こうき"},{"win_team_name":"赤いきつね","win_team_mvp":"ノム"},{"win_team_name":"赤いきつね","win_team_mvp":"マシュマロ"},{"win_team_name":"赤いきつね","win_team_mvp":"しょてん"},{"win_team_name":"緑のたぬき","win_team_mvp":"ライトマン"},{"win_team_name":"赤いきつね","win_team_mvp":"ヒロミンツ"},{"win_team_name":"赤いきつね","win_team_mvp":"(・ω・)"},{"win_team_name":"赤いきつね","win_team_mvp":"カゲツグ"},{"win_team_name":"赤いきつね","win_team_mvp":"?$!!"},{"win_team_name":"赤いきつね","win_team_mvp":"ゴミ"}]