[{"win_team_name":"ツッコミ","win_team_mvp":"どっこいパブロガール"},{"win_team_name":"ツッコミ","win_team_mvp":"まり"},{"win_team_name":"ボケ","win_team_mvp":"やまっち"},{"win_team_name":"ツッコミ","win_team_mvp":"アカリ"},{"win_team_name":"ボケ","win_team_mvp":"ねむっぽいなにか"},{"win_team_name":"ツッコミ","win_team_mvp":"アーサー"},{"win_team_name":"ツッコミ","win_team_mvp":"ゆき"},{"win_team_name":"ボケ","win_team_mvp":"おにおん"},{"win_team_name":"ツッコミ","win_team_mvp":"Yuzu"},{"win_team_name":"ボケ","win_team_mvp":"リョーマ"},{"win_team_name":"ボケ","win_team_mvp":"つうてやん"},{"win_team_name":"ボケ","win_team_mvp":"ひゅうがなつ"},{"win_team_name":"ボケ","win_team_mvp":"あたりめいどだおdc"},{"win_team_name":"ツッコミ","win_team_mvp":"はると!"},{"win_team_name":"ツッコミ","win_team_mvp":"かんた"},{"win_team_name":"ツッコミ","win_team_mvp":"ルフィ"},{"win_team_name":"ツッコミ","win_team_mvp":"アルマジロ"},{"win_team_name":"ツッコミ","win_team_mvp":"きよる"},{"win_team_name":"ボケ","win_team_mvp":"しょうり"},{"win_team_name":"ボケ","win_team_mvp":"feifon78"},{"win_team_name":"ツッコミ","win_team_mvp":"けさお"},{"win_team_name":"ツッコミ","win_team_mvp":"はやと"},{"win_team_name":"ツッコミ","win_team_mvp":"とうい"},{"win_team_name":"ボケ","win_team_mvp":"しづ"},{"win_team_name":"ボケ","win_team_mvp":"ジュン"},{"win_team_name":"ツッコミ","win_team_mvp":"umi"},{"win_team_name":"ツッコミ","win_team_mvp":"U-3"},{"win_team_name":"ボケ","win_team_mvp":"むぎちゃ"},{"win_team_name":"ツッコミ","win_team_mvp":"アイリ"},{"win_team_name":"ボケ","win_team_mvp":"カル"},{"win_team_name":"ボケ","win_team_mvp":"ぱずー"},{"win_team_name":"ツッコミ","win_team_mvp":"あたりめ"},{"win_team_name":"ボケ","win_team_mvp":"あおい"},{"win_team_name":"ボケ","win_team_mvp":"りょう"},{"win_team_name":"ボケ","win_team_mvp":"ちゅうにびょう"},{"win_team_name":"ツッコミ","win_team_mvp":"ライロウ"},{"win_team_name":"ボケ","win_team_mvp":"たくまっちょ"},{"win_team_name":"ツッコミ","win_team_mvp":"taka"},{"win_team_name":"ツッコミ","win_team_mvp":"ゆう"},{"win_team_name":"ツッコミ","win_team_mvp":"ななみ"},{"win_team_name":"ボケ","win_team_mvp":"きいち"},{"win_team_name":"ボケ","win_team_mvp":"FIERO"},{"win_team_name":"ボケ","win_team_mvp":"せいねんD"},{"win_team_name":"ボケ","win_team_mvp":"ひでき"},{"win_team_name":"ボケ","win_team_mvp":"たる"},{"win_team_name":"ボケ","win_team_mvp":"てれび"},{"win_team_name":"ツッコミ","win_team_mvp":"こざかな"},{"win_team_name":"ボケ","win_team_mvp":"ひかちょん"},{"win_team_name":"ツッコミ","win_team_mvp":"かずや"},{"win_team_name":"ボケ","win_team_mvp":"GRP-クシナダ"},{"win_team_name":"ツッコミ","win_team_mvp":"イツキ"},{"win_team_name":"ツッコミ","win_team_mvp":"ヒビキ"},{"win_team_name":"ボケ","win_team_mvp":"きゅうり"},{"win_team_name":"ツッコミ","win_team_mvp":"リクライニングシート"},{"win_team_name":"ボケ","win_team_mvp":"take."},{"win_team_name":"ボケ","win_team_mvp":"(ToT)"},{"win_team_name":"ボケ","win_team_mvp":"ひゃだるこMK-2"},{"win_team_name":"ボケ","win_team_mvp":"とぅるーす"},{"win_team_name":"ボケ","win_team_mvp":"はると"},{"win_team_name":"ボケ","win_team_mvp":"ぽるく"},{"win_team_name":"ボケ","win_team_mvp":"たなか"},{"win_team_name":"ボケ","win_team_mvp":"Killcy"},{"win_team_name":"ボケ","win_team_mvp":"とも"},{"win_team_name":"ツッコミ","win_team_mvp":"(そ・∀・ら)"},{"win_team_name":"ボケ","win_team_mvp":"とにょー"},{"win_team_name":"ツッコミ","win_team_mvp":"きゃりーぱぴゅぱぴゅ"},{"win_team_name":"ボケ","win_team_mvp":"みくす"},{"win_team_name":"ツッコミ","win_team_mvp":"くるくる"},{"win_team_name":"ツッコミ","win_team_mvp":"yositaka"},{"win_team_name":"ツッコミ","win_team_mvp":"ZERO"},{"win_team_name":"ボケ","win_team_mvp":"たいちゃん"},{"win_team_name":"ボケ","win_team_mvp":"とも"},{"win_team_name":"ツッコミ","win_team_mvp":"オヤ"},{"win_team_name":"ツッコミ","win_team_mvp":"・×・"},{"win_team_name":"ツッコミ","win_team_mvp":"だいち"},{"win_team_name":"ツッコミ","win_team_mvp":"sideB"},{"win_team_name":"ツッコミ","win_team_mvp":"プリン"},{"win_team_name":"ボケ","win_team_mvp":"あけい"},{"win_team_name":"ツッコミ","win_team_mvp":"きい"},{"win_team_name":"ツッコミ","win_team_mvp":"Jack-ruin"},{"win_team_name":"ツッコミ","win_team_mvp":"kunirx7"},{"win_team_name":"ツッコミ","win_team_mvp":"チビロス"},{"win_team_name":"ボケ","win_team_mvp":"クッぱぱ"},{"win_team_name":"ボケ","win_team_mvp":"Daisuke"},{"win_team_name":"ボケ","win_team_mvp":"ねむり"},{"win_team_name":"ツッコミ","win_team_mvp":"べる"},{"win_team_name":"ボケ","win_team_mvp":"レイ"},{"win_team_name":"ボケ","win_team_mvp":"ふうま"},{"win_team_name":"ボケ","win_team_mvp":"けーた"},{"win_team_name":"ツッコミ","win_team_mvp":"マナトゥーーン!!"},{"win_team_name":"ボケ","win_team_mvp":"KEE"}]