[{"win_team_name":"ボケ","win_team_mvp":"あ"},{"win_team_name":"ツッコミ","win_team_mvp":"みずアサギ"},{"win_team_name":"ボケ","win_team_mvp":"くろやぎちゃん"},{"win_team_name":"ツッコミ","win_team_mvp":"¶§クリアタマ仝"},{"win_team_name":"ツッコミ","win_team_mvp":"リッチー"},{"win_team_name":"ボケ","win_team_mvp":"みり"},{"win_team_name":"ツッコミ","win_team_mvp":"リヴァー"},{"win_team_name":"ボケ","win_team_mvp":"たってぃ"},{"win_team_name":"ボケ","win_team_mvp":"?"},{"win_team_name":"ツッコミ","win_team_mvp":"ともしび"},{"win_team_name":"ボケ","win_team_mvp":"たくと"},{"win_team_name":"ツッコミ","win_team_mvp":"あずき"},{"win_team_name":"ツッコミ","win_team_mvp":"さたん"},{"win_team_name":"ボケ","win_team_mvp":"れじぇんど"},{"win_team_name":"ツッコミ","win_team_mvp":"たいき"},{"win_team_name":"ボケ","win_team_mvp":"ゆりしー"},{"win_team_name":"ツッコミ","win_team_mvp":"なまもの"},{"win_team_name":"ツッコミ","win_team_mvp":"じょるの"},{"win_team_name":"ツッコミ","win_team_mvp":"lmiria"},{"win_team_name":"ボケ","win_team_mvp":"さくら"},{"win_team_name":"ボケ","win_team_mvp":"ヒーロー"},{"win_team_name":"ツッコミ","win_team_mvp":"あべべん"},{"win_team_name":"ボケ","win_team_mvp":"レッカーちゅうい"},{"win_team_name":"ボケ","win_team_mvp":"とづけー"},{"win_team_name":"ボケ","win_team_mvp":"はるき"},{"win_team_name":"ツッコミ","win_team_mvp":"かねやん"},{"win_team_name":"ツッコミ","win_team_mvp":"リューサン"},{"win_team_name":"ボケ","win_team_mvp":"きさんた"},{"win_team_name":"ツッコミ","win_team_mvp":"ずんだもち"},{"win_team_name":"ボケ","win_team_mvp":"こなつ"},{"win_team_name":"ボケ","win_team_mvp":"yoshi"},{"win_team_name":"ツッコミ","win_team_mvp":"うみ"},{"win_team_name":"ボケ","win_team_mvp":"ぜったいころすマン"},{"win_team_name":"ボケ","win_team_mvp":"りょうちゃん"},{"win_team_name":"ボケ","win_team_mvp":"イキスギィ!!"},{"win_team_name":"ツッコミ","win_team_mvp":"tokia"},{"win_team_name":"ツッコミ","win_team_mvp":"squid.3"},{"win_team_name":"ツッコミ","win_team_mvp":"ばつまる"},{"win_team_name":"ツッコミ","win_team_mvp":"りゅうせい"},{"win_team_name":"ボケ","win_team_mvp":"つぶぴょん"},{"win_team_name":"ツッコミ","win_team_mvp":"つばさ"},{"win_team_name":"ボケ","win_team_mvp":"KUV"},{"win_team_name":"ツッコミ","win_team_mvp":"りん"},{"win_team_name":"ボケ","win_team_mvp":"トニー"},{"win_team_name":"ボケ","win_team_mvp":"たんぱん"},{"win_team_name":"ボケ","win_team_mvp":"ルーブレン"},{"win_team_name":"ツッコミ","win_team_mvp":"G"},{"win_team_name":"ボケ","win_team_mvp":"エリアス"},{"win_team_name":"ツッコミ","win_team_mvp":"イカガール(・∀・)"},{"win_team_name":"ボケ","win_team_mvp":"ところてん2ごう"},{"win_team_name":"ボケ","win_team_mvp":"AttoCom"},{"win_team_name":"ツッコミ","win_team_mvp":"ばえる"},{"win_team_name":"ボケ","win_team_mvp":"†スカル†.CROW"},{"win_team_name":"ボケ","win_team_mvp":"ゆうと"},{"win_team_name":"ツッコミ","win_team_mvp":"アル"},{"win_team_name":"ボケ","win_team_mvp":"ちぃ"},{"win_team_name":"ボケ","win_team_mvp":"おかエモン^^"},{"win_team_name":"ツッコミ","win_team_mvp":"えいえんてつだうマン"},{"win_team_name":"ツッコミ","win_team_mvp":"のん"},{"win_team_name":"ツッコミ","win_team_mvp":"cuturn"},{"win_team_name":"ボケ","win_team_mvp":"まっひー"},{"win_team_name":"ツッコミ","win_team_mvp":"NANA"},{"win_team_name":"ツッコミ","win_team_mvp":"パパ"},{"win_team_name":"ツッコミ","win_team_mvp":"たれぞう"},{"win_team_name":"ボケ","win_team_mvp":"かんた"},{"win_team_name":"ツッコミ","win_team_mvp":"きむち"},{"win_team_name":"ボケ","win_team_mvp":"ぴよこ"},{"win_team_name":"ツッコミ","win_team_mvp":"kukky.jp"},{"win_team_name":"ボケ","win_team_mvp":"さつい"},{"win_team_name":"ツッコミ","win_team_mvp":"さあちゃん"},{"win_team_name":"ツッコミ","win_team_mvp":"タマちゃん"},{"win_team_name":"ボケ","win_team_mvp":"ひめもり"},{"win_team_name":"ボケ","win_team_mvp":"まどつき"},{"win_team_name":"ツッコミ","win_team_mvp":"ぬへと"},{"win_team_name":"ツッコミ","win_team_mvp":"みうらなおき"},{"win_team_name":"ボケ","win_team_mvp":"モー"},{"win_team_name":"ツッコミ","win_team_mvp":"そうま"},{"win_team_name":"ツッコミ","win_team_mvp":"Itda"},{"win_team_name":"ボケ","win_team_mvp":"しゅうと"},{"win_team_name":"ツッコミ","win_team_mvp":"みそスーフ。"},{"win_team_name":"ボケ","win_team_mvp":"うめちゃ"},{"win_team_name":"ツッコミ","win_team_mvp":"はると"},{"win_team_name":"ボケ","win_team_mvp":"まめつぶ☆りゅうぼく"},{"win_team_name":"ツッコミ","win_team_mvp":"がくせい"},{"win_team_name":"ボケ","win_team_mvp":"こぞう"},{"win_team_name":"ツッコミ","win_team_mvp":"ぽんず"},{"win_team_name":"ツッコミ","win_team_mvp":"ともさん"},{"win_team_name":"ボケ","win_team_mvp":"こうめい"},{"win_team_name":"ボケ","win_team_mvp":"すあま"},{"win_team_name":"ボケ","win_team_mvp":"おちび"},{"win_team_name":"ボケ","win_team_mvp":"サティスファクション"},{"win_team_name":"ツッコミ","win_team_mvp":"あおい"}]