[{"win_team_name":"ツッコミ","win_team_mvp":"ウデマエZ"},{"win_team_name":"ツッコミ","win_team_mvp":"グラたん"},{"win_team_name":"ツッコミ","win_team_mvp":"たろーぅ"},{"win_team_name":"ツッコミ","win_team_mvp":"ユリ"},{"win_team_name":"ボケ","win_team_mvp":"さき"},{"win_team_name":"ボケ","win_team_mvp":"つな"},{"win_team_name":"ボケ","win_team_mvp":"はると"},{"win_team_name":"ツッコミ","win_team_mvp":"カイリ.Stern"},{"win_team_name":"ツッコミ","win_team_mvp":"ヤミー"},{"win_team_name":"ツッコミ","win_team_mvp":"りんたろう"},{"win_team_name":"ボケ","win_team_mvp":"きんじょのパンやさん"},{"win_team_name":"ツッコミ","win_team_mvp":"なべ"},{"win_team_name":"ボケ","win_team_mvp":"スルメ"},{"win_team_name":"ツッコミ","win_team_mvp":"Ren"},{"win_team_name":"ボケ","win_team_mvp":"みずな"},{"win_team_name":"ツッコミ","win_team_mvp":"PLMR"},{"win_team_name":"ツッコミ","win_team_mvp":"ひよこ"},{"win_team_name":"ツッコミ","win_team_mvp":"Miyurisata"},{"win_team_name":"ボケ","win_team_mvp":"セリ"},{"win_team_name":"ツッコミ","win_team_mvp":"よしひで"},{"win_team_name":"ボケ","win_team_mvp":"QB"},{"win_team_name":"ツッコミ","win_team_mvp":"インドリ"},{"win_team_name":"ツッコミ","win_team_mvp":"じゅんじ"},{"win_team_name":"ボケ","win_team_mvp":"イカガッチャ"},{"win_team_name":"ツッコミ","win_team_mvp":"れぃ"},{"win_team_name":"ツッコミ","win_team_mvp":"りきてん*ハマー"},{"win_team_name":"ツッコミ","win_team_mvp":"くぅく"},{"win_team_name":"ツッコミ","win_team_mvp":"りき"},{"win_team_name":"ツッコミ","win_team_mvp":"たかあき"},{"win_team_name":"ボケ","win_team_mvp":"kokoharu"},{"win_team_name":"ボケ","win_team_mvp":"AdPe)チップ"},{"win_team_name":"ツッコミ","win_team_mvp":"イカとっきー"},{"win_team_name":"ボケ","win_team_mvp":"りぜ"},{"win_team_name":"ボケ","win_team_mvp":"クロネコ"},{"win_team_name":"ツッコミ","win_team_mvp":"hiryu　くコ:ミ"},{"win_team_name":"ボケ","win_team_mvp":"きんようはカレーのひ"},{"win_team_name":"ツッコミ","win_team_mvp":"じんちくむがいなやつ"},{"win_team_name":"ボケ","win_team_mvp":"あのねこ"},{"win_team_name":"ボケ","win_team_mvp":"フェンリル"},{"win_team_name":"ツッコミ","win_team_mvp":"なゆ(⌒,_ゝ⌒)た"},{"win_team_name":"ツッコミ","win_team_mvp":"まかだみあ/*"},{"win_team_name":"ツッコミ","win_team_mvp":"アル・イカポネ"},{"win_team_name":"ツッコミ","win_team_mvp":"★☆kaaa☆★"},{"win_team_name":"ボケ","win_team_mvp":"ゆいと"},{"win_team_name":"ボケ","win_team_mvp":"てらゆ"},{"win_team_name":"ボケ","win_team_mvp":"SARI"},{"win_team_name":"ボケ","win_team_mvp":"てきいはありません!"},{"win_team_name":"ツッコミ","win_team_mvp":"あやか"},{"win_team_name":"ボケ","win_team_mvp":"クニヒロ"},{"win_team_name":"ボケ","win_team_mvp":"1P"},{"win_team_name":"ボケ","win_team_mvp":"フルハタ"},{"win_team_name":"ボケ","win_team_mvp":"えいえんのししゃも"},{"win_team_name":"ツッコミ","win_team_mvp":"yukihir0"},{"win_team_name":"ボケ","win_team_mvp":"なるかみ"},{"win_team_name":"ボケ","win_team_mvp":"ぷーさん"},{"win_team_name":"ボケ","win_team_mvp":"†なつき†"},{"win_team_name":"ツッコミ","win_team_mvp":"すかい"},{"win_team_name":"ボケ","win_team_mvp":"すずな☆★"},{"win_team_name":"ボケ","win_team_mvp":"ウィンド"},{"win_team_name":"ツッコミ","win_team_mvp":"なんてこった!ケニー"},{"win_team_name":"ボケ","win_team_mvp":"くコ:ミ======"},{"win_team_name":"ボケ","win_team_mvp":"よわきひと"},{"win_team_name":"ツッコミ","win_team_mvp":"どぴゅむ[765]"},{"win_team_name":"ボケ","win_team_mvp":"あさは"},{"win_team_name":"ボケ","win_team_mvp":"こんがり♪ちはちゃん"},{"win_team_name":"ツッコミ","win_team_mvp":"わたる"},{"win_team_name":"ボケ","win_team_mvp":"ゆーいち"},{"win_team_name":"ツッコミ","win_team_mvp":"あっかりーん"},{"win_team_name":"ツッコミ","win_team_mvp":"みぃ"},{"win_team_name":"ツッコミ","win_team_mvp":"しゃるみょん"},{"win_team_name":"ボケ","win_team_mvp":"ひろパくん"},{"win_team_name":"ボケ","win_team_mvp":"ともみ"},{"win_team_name":"ボケ","win_team_mvp":"ぼんねろ"},{"win_team_name":"ボケ","win_team_mvp":"『　 』(WiiU)"},{"win_team_name":"ツッコミ","win_team_mvp":"れいおん"},{"win_team_name":"ボケ","win_team_mvp":"マチャミ"},{"win_team_name":"ツッコミ","win_team_mvp":"あんこ"},{"win_team_name":"ツッコミ","win_team_mvp":"あたる"},{"win_team_name":"ボケ","win_team_mvp":"モリ"},{"win_team_name":"ツッコミ","win_team_mvp":"まっちゃ"},{"win_team_name":"ツッコミ","win_team_mvp":"ひしょう"},{"win_team_name":"ボケ","win_team_mvp":"キラキラ"},{"win_team_name":"ボケ","win_team_mvp":"せぐっちー"},{"win_team_name":"ボケ","win_team_mvp":"でんどろー"},{"win_team_name":"ボケ","win_team_mvp":"nich"},{"win_team_name":"ツッコミ","win_team_mvp":"Sleagh"},{"win_team_name":"ツッコミ","win_team_mvp":"エビハラ"},{"win_team_name":"ツッコミ","win_team_mvp":"かづ"},{"win_team_name":"ボケ","win_team_mvp":"さやか"},{"win_team_name":"ボケ","win_team_mvp":"кαиα."},{"win_team_name":"ツッコミ","win_team_mvp":"かなしみのごま; ;"}]