[{"win_team_name":"ミルクティー","win_team_mvp":"るい"},{"win_team_name":"ミルクティー","win_team_mvp":"どく"},{"win_team_name":"ミルクティー","win_team_mvp":"あすだふ"},{"win_team_name":"ミルクティー","win_team_mvp":"k"},{"win_team_name":"ミルクティー","win_team_mvp":"りかちゅう"},{"win_team_name":"レモンティー","win_team_mvp":"てっしー"},{"win_team_name":"ミルクティー","win_team_mvp":"ルミヲ"},{"win_team_name":"レモンティー","win_team_mvp":"けんきょなイ"},{"win_team_name":"ミルクティー","win_team_mvp":"おやつカルパ"},{"win_team_name":"ミルクティー","win_team_mvp":"ラッツ"},{"win_team_name":"レモンティー","win_team_mvp":"ロケットダイ"},{"win_team_name":"レモンティー","win_team_mvp":"たっつー"},{"win_team_name":"レモンティー","win_team_mvp":"ぱっといかん"},{"win_team_name":"ミルクティー","win_team_mvp":"みゃん"},{"win_team_name":"ミルクティー","win_team_mvp":"ひぐま"},{"win_team_name":"ミルクティー","win_team_mvp":"バルサチック"},{"win_team_name":"レモンティー","win_team_mvp":"すみれ"},{"win_team_name":"ミルクティー","win_team_mvp":"4410"},{"win_team_name":"レモンティー","win_team_mvp":"こうへい"},{"win_team_name":"ミルクティー","win_team_mvp":"(^-^)/"},{"win_team_name":"ミルクティー","win_team_mvp":"やマモと"},{"win_team_name":"レモンティー","win_team_mvp":"SoziRo"},{"win_team_name":"ミルクティー","win_team_mvp":"サミダレ"},{"win_team_name":"ミルクティー","win_team_mvp":"だなも"},{"win_team_name":"ミルクティー","win_team_mvp":"るぱん"},{"win_team_name":"レモンティー","win_team_mvp":"ルー"},{"win_team_name":"レモンティー","win_team_mvp":"とむえる"},{"win_team_name":"レモンティー","win_team_mvp":"ねこだまし　"},{"win_team_name":"レモンティー","win_team_mvp":"みうらだいせ"},{"win_team_name":"レモンティー","win_team_mvp":"らん!"},{"win_team_name":"ミルクティー","win_team_mvp":"モンステラ"},{"win_team_name":"ミルクティー","win_team_mvp":"ダイナモころ"},{"win_team_name":"ミルクティー","win_team_mvp":"IFL_ゆうき"},{"win_team_name":"レモンティー","win_team_mvp":"Pepon"},{"win_team_name":"ミルクティー","win_team_mvp":"よしと"},{"win_team_name":"レモンティー","win_team_mvp":"しにがみパブ"},{"win_team_name":"ミルクティー","win_team_mvp":"ぐっち"},{"win_team_name":"レモンティー","win_team_mvp":"MISS"},{"win_team_name":"レモンティー","win_team_mvp":"Adam"},{"win_team_name":"レモンティー","win_team_mvp":"Wingさん"},{"win_team_name":"ミルクティー","win_team_mvp":"うっしー"},{"win_team_name":"ミルクティー","win_team_mvp":"いつき"},{"win_team_name":"レモンティー","win_team_mvp":"つのだ"},{"win_team_name":"ミルクティー","win_team_mvp":"はるの"},{"win_team_name":"ミルクティー","win_team_mvp":"はくろう"},{"win_team_name":"ミルクティー","win_team_mvp":"ガチメガネ"},{"win_team_name":"ミルクティー","win_team_mvp":"PLAYER"},{"win_team_name":"レモンティー","win_team_mvp":"(・3・)～♪"},{"win_team_name":"ミルクティー","win_team_mvp":"ぬぅ.Zip"},{"win_team_name":"レモンティー","win_team_mvp":"ぱふべる"},{"win_team_name":"ミルクティー","win_team_mvp":"レモネード"},{"win_team_name":"レモンティー","win_team_mvp":"でめまよ"},{"win_team_name":"ミルクティー","win_team_mvp":"cazuyan"},{"win_team_name":"ミルクティー","win_team_mvp":"しょうき"},{"win_team_name":"ミルクティー","win_team_mvp":"はけん♪"},{"win_team_name":"レモンティー","win_team_mvp":"ぼりぼり"},{"win_team_name":"レモンティー","win_team_mvp":"ぷりを"},{"win_team_name":"ミルクティー","win_team_mvp":"マリトフ"},{"win_team_name":"レモンティー","win_team_mvp":"あたま"},{"win_team_name":"ミルクティー","win_team_mvp":"ざわわ"},{"win_team_name":"ミルクティー","win_team_mvp":"ひばち"},{"win_team_name":"ミルクティー","win_team_mvp":"ぱこ"},{"win_team_name":"ミルクティー","win_team_mvp":"chicory"},{"win_team_name":"ミルクティー","win_team_mvp":"かえで"},{"win_team_name":"ミルクティー","win_team_mvp":"hiro"},{"win_team_name":"ミルクティー","win_team_mvp":"プロテイン☆"},{"win_team_name":"ミルクティー","win_team_mvp":"たー"},{"win_team_name":"レモンティー","win_team_mvp":"ひで"},{"win_team_name":"ミルクティー","win_team_mvp":"しゅん"},{"win_team_name":"レモンティー","win_team_mvp":"まゆげ"},{"win_team_name":"ミルクティー","win_team_mvp":"u"},{"win_team_name":"ミルクティー","win_team_mvp":"そら"},{"win_team_name":"レモンティー","win_team_mvp":"ぬこ☆がみ"},{"win_team_name":"レモンティー","win_team_mvp":"よっちゃん"},{"win_team_name":"ミルクティー","win_team_mvp":"Lovivin"},{"win_team_name":"レモンティー","win_team_mvp":"MMC(jp)"},{"win_team_name":"ミルクティー","win_team_mvp":"ふかあまりゴ"},{"win_team_name":"ミルクティー","win_team_mvp":"ぱに"},{"win_team_name":"レモンティー","win_team_mvp":"はる"},{"win_team_name":"ミルクティー","win_team_mvp":"moai"},{"win_team_name":"レモンティー","win_team_mvp":"ポチ"},{"win_team_name":"ミルクティー","win_team_mvp":"ドラちゃんた"},{"win_team_name":"ミルクティー","win_team_mvp":"ちび"},{"win_team_name":"レモンティー","win_team_mvp":"シノブ"},{"win_team_name":"ミルクティー","win_team_mvp":"イカのおやつ"},{"win_team_name":"ミルクティー","win_team_mvp":"Katty.96"},{"win_team_name":"ミルクティー","win_team_mvp":"グレートマッ"},{"win_team_name":"ミルクティー","win_team_mvp":"しろバラコー"},{"win_team_name":"レモンティー","win_team_mvp":"きょんてぃ"},{"win_team_name":"ミルクティー","win_team_mvp":"みかりん"},{"win_team_name":"レモンティー","win_team_mvp":"くりごはんと"},{"win_team_name":"ミルクティー","win_team_mvp":"テンキー"}]