[{"win_team_name":"レモンティー","win_team_mvp":"ひつき"},{"win_team_name":"レモンティー","win_team_mvp":"すず*りんご"},{"win_team_name":"ミルクティー","win_team_mvp":"ゆーご"},{"win_team_name":"ミルクティー","win_team_mvp":"KED"},{"win_team_name":"ミルクティー","win_team_mvp":"SOKUKO"},{"win_team_name":"ミルクティー","win_team_mvp":"ひで"},{"win_team_name":"レモンティー","win_team_mvp":"HD"},{"win_team_name":"ミルクティー","win_team_mvp":"ゆーきゃん"},{"win_team_name":"レモンティー","win_team_mvp":"ピットくんぺ"},{"win_team_name":"ミルクティー","win_team_mvp":"こっちゃん"},{"win_team_name":"ミルクティー","win_team_mvp":"まっつ"},{"win_team_name":"ミルクティー","win_team_mvp":"ウッディ"},{"win_team_name":"ミルクティー","win_team_mvp":"からさ"},{"win_team_name":"ミルクティー","win_team_mvp":"うんぽこ"},{"win_team_name":"ミルクティー","win_team_mvp":"まあ.mocchi"},{"win_team_name":"ミルクティー","win_team_mvp":"もーちゃん"},{"win_team_name":"ミルクティー","win_team_mvp":"よしお"},{"win_team_name":"レモンティー","win_team_mvp":"けいくん"},{"win_team_name":"レモンティー","win_team_mvp":"ヒロ"},{"win_team_name":"ミルクティー","win_team_mvp":"マヌ"},{"win_team_name":"ミルクティー","win_team_mvp":"ケルヴ"},{"win_team_name":"レモンティー","win_team_mvp":"そうひ"},{"win_team_name":"ミルクティー","win_team_mvp":"まるよし"},{"win_team_name":"ミルクティー","win_team_mvp":"USDK"},{"win_team_name":"ミルクティー","win_team_mvp":"Miyu..*"},{"win_team_name":"ミルクティー","win_team_mvp":"じろう"},{"win_team_name":"レモンティー","win_team_mvp":"けんじ"},{"win_team_name":"ミルクティー","win_team_mvp":"ゆうた"},{"win_team_name":"ミルクティー","win_team_mvp":"マツ"},{"win_team_name":"ミルクティー","win_team_mvp":"ひろき"},{"win_team_name":"レモンティー","win_team_mvp":"けつ"},{"win_team_name":"ミルクティー","win_team_mvp":"さと"},{"win_team_name":"ミルクティー","win_team_mvp":"(Nintendo)"},{"win_team_name":"レモンティー","win_team_mvp":"たかよし"},{"win_team_name":"ミルクティー","win_team_mvp":"ベヌウ"},{"win_team_name":"レモンティー","win_team_mvp":"タカシ"},{"win_team_name":"レモンティー","win_team_mvp":"†‡ちさと‡"},{"win_team_name":"レモンティー","win_team_mvp":"けんと"},{"win_team_name":"レモンティー","win_team_mvp":"れと"},{"win_team_name":"レモンティー","win_team_mvp":"こはく"},{"win_team_name":"ミルクティー","win_team_mvp":"そうくん"},{"win_team_name":"ミルクティー","win_team_mvp":"しのび"},{"win_team_name":"レモンティー","win_team_mvp":"なな"},{"win_team_name":"レモンティー","win_team_mvp":"けい"},{"win_team_name":"ミルクティー","win_team_mvp":"とうふ"},{"win_team_name":"レモンティー","win_team_mvp":"ローラ"},{"win_team_name":"ミルクティー","win_team_mvp":"ね-こ"},{"win_team_name":"レモンティー","win_team_mvp":"しゅういち"},{"win_team_name":"レモンティー","win_team_mvp":"みほ"},{"win_team_name":"ミルクティー","win_team_mvp":"ショッピー"},{"win_team_name":"ミルクティー","win_team_mvp":"リョーキ"},{"win_team_name":"レモンティー","win_team_mvp":"だいち"},{"win_team_name":"レモンティー","win_team_mvp":"ゆう"},{"win_team_name":"レモンティー","win_team_mvp":"けんせい"},{"win_team_name":"レモンティー","win_team_mvp":"ちゃめ"},{"win_team_name":"レモンティー","win_team_mvp":"はやて"},{"win_team_name":"ミルクティー","win_team_mvp":"なるみ"},{"win_team_name":"ミルクティー","win_team_mvp":"みづき"},{"win_team_name":"レモンティー","win_team_mvp":"ぎぃぎ"},{"win_team_name":"レモンティー","win_team_mvp":"K.A"},{"win_team_name":"ミルクティー","win_team_mvp":"まつむー"},{"win_team_name":"レモンティー","win_team_mvp":"RXロト8"},{"win_team_name":"レモンティー","win_team_mvp":"ケイ"},{"win_team_name":"ミルクティー","win_team_mvp":"dochii"},{"win_team_name":"レモンティー","win_team_mvp":"きょうすけ"},{"win_team_name":"レモンティー","win_team_mvp":"はるき"},{"win_team_name":"ミルクティー","win_team_mvp":"ロロノア●ゾ"},{"win_team_name":"レモンティー","win_team_mvp":"ふーひー"},{"win_team_name":"ミルクティー","win_team_mvp":"なゆねこ"},{"win_team_name":"レモンティー","win_team_mvp":"もとむ"},{"win_team_name":"レモンティー","win_team_mvp":"けんご"},{"win_team_name":"ミルクティー","win_team_mvp":"ミツバ"},{"win_team_name":"レモンティー","win_team_mvp":"しえマン"},{"win_team_name":"ミルクティー","win_team_mvp":"りん"},{"win_team_name":"ミルクティー","win_team_mvp":"ゆうや"},{"win_team_name":"レモンティー","win_team_mvp":"せいんと　と"},{"win_team_name":"レモンティー","win_team_mvp":"いそはち"},{"win_team_name":"ミルクティー","win_team_mvp":"とうちゃん"},{"win_team_name":"ミルクティー","win_team_mvp":"ルイ"},{"win_team_name":"レモンティー","win_team_mvp":"りくぼう"},{"win_team_name":"ミルクティー","win_team_mvp":"Keito"},{"win_team_name":"レモンティー","win_team_mvp":"おかぴ"},{"win_team_name":"レモンティー","win_team_mvp":"えるじぇー"},{"win_team_name":"ミルクティー","win_team_mvp":"ねぼすけ"},{"win_team_name":"レモンティー","win_team_mvp":"いおり"},{"win_team_name":"レモンティー","win_team_mvp":"フナナンちゃ"},{"win_team_name":"レモンティー","win_team_mvp":"セツナ・グレ"},{"win_team_name":"ミルクティー","win_team_mvp":"【ざわわ™】"},{"win_team_name":"ミルクティー","win_team_mvp":"こうちゃん"},{"win_team_name":"ミルクティー","win_team_mvp":"YOU"},{"win_team_name":"ミルクティー","win_team_mvp":"Tomohiro"},{"win_team_name":"レモンティー","win_team_mvp":"かず"},{"win_team_name":"レモンティー","win_team_mvp":"mlon"}]